dremioarrow/__init__.py
dremioarrow/client.py
dremio_arrow-1.0.3.dist-info/LICENSE
dremio_arrow-1.0.3.dist-info/METADATA
dremio_arrow-1.0.3.dist-info/WHEEL
dremio_arrow-1.0.3.dist-info/RECORD
