Metadata-Version: 2.1
Name: dremio-arrow
Version: 1.0.3
Summary: Dremio SQL Lakehouse Arrow Flight Client.
Home-page: https://github.com/jaysnm/dremio-arrow
License: Apache-2.0
Author: Jason Kinyua
Author-email: jaysnmury@gmail.com
Requires-Python: >=3.10,<3.12
Classifier: Development Status :: 5 - Production/Stable
Classifier: Intended Audience :: Developers
Classifier: License :: OSI Approved :: Apache Software License
Classifier: Natural Language :: English
Classifier: Programming Language :: Python :: 3
Classifier: Programming Language :: Python :: 3.10
Classifier: Programming Language :: Python :: 3.11
Provides-Extra: dev
Provides-Extra: doc
Provides-Extra: test
Provides-Extra: toy
Requires-Dist: black (>=23.3.0,<24.0.0) ; extra == "test"
Requires-Dist: bump2version (>=1.0.1,<2.0.0) ; extra == "dev"
Requires-Dist: flake8 (==5.0.4) ; extra == "test"
Requires-Dist: flake8-docstrings (>=1.7.0,<2.0.0) ; extra == "test"
Requires-Dist: ipython (>=8.14.0,<9.0.0) ; extra == "toy"
Requires-Dist: isort (>=5.12.0,<6.0.0) ; extra == "test"
Requires-Dist: jupyterlab (>=4.0.2,<5.0.0) ; extra == "toy"
Requires-Dist: mkdocs (>=1.4.3,<2.0.0) ; extra == "doc"
Requires-Dist: mkdocs-autorefs (>=0.4.1,<0.5.0) ; extra == "doc"
Requires-Dist: mkdocs-git-revision-date-localized-plugin (>=1.2.0,<2.0.0) ; extra == "doc"
Requires-Dist: mkdocs-include-markdown-plugin (>=4.0.4,<5.0.0) ; extra == "doc"
Requires-Dist: mkdocs-material (>=9.1.18,<10.0.0) ; extra == "doc"
Requires-Dist: mkdocs-material-extensions (>=1.1.1,<2.0.0)
Requires-Dist: mkdocstrings (>=0.22.0,<0.23.0) ; extra == "doc"
Requires-Dist: mkdocstrings-python (>=1.1.2,<2.0.0)
Requires-Dist: mypy (>=1.4.1,<2.0.0) ; extra == "test"
Requires-Dist: pandas (>=2.0.3,<3.0.0)
Requires-Dist: pre-commit (>=3.3.3,<4.0.0) ; extra == "dev"
Requires-Dist: pyarrow (>=12.0.1,<13.0.0)
Requires-Dist: pytest (>=7.4.0,<8.0.0) ; extra == "test"
Requires-Dist: pytest-cov (>=4.1.0,<5.0.0) ; extra == "test"
Requires-Dist: requests (>=2.31.0,<3.0.0) ; extra == "dev"
Requires-Dist: tornado (>=6.3.2,<7.0.0)
Requires-Dist: types-requests (>=2.31.0.1,<3.0.0.0) ; extra == "dev"
Requires-Dist: virtualenv (==20.13.2) ; extra == "dev"
